umbrella_monitor/__init__.py
umbrella_monitor/__main__.py
umbrella_monitor/toml_config_mgr.py
umbrella_monitor-1.0.1.dist-info/LICENSE
umbrella_monitor-1.0.1.dist-info/METADATA
umbrella_monitor-1.0.1.dist-info/WHEEL
umbrella_monitor-1.0.1.dist-info/top_level.txt
umbrella_monitor-1.0.1.dist-info/RECORD
